README.md
setup.py
./pyimgbatch/__init__.py
./pyimgbatch/__main__.py
./pyimgbatch/pyimgbatch.py
pyimgbatch/__init__.py
pyimgbatch/__main__.py
pyimgbatch/pyimgbatch.py
pyimgbatch.egg-info/PKG-INFO
pyimgbatch.egg-info/SOURCES.txt
pyimgbatch.egg-info/dependency_links.txt
pyimgbatch.egg-info/entry_points.txt
pyimgbatch.egg-info/requires.txt
pyimgbatch.egg-info/top_level.txt